fvwmpy/__init__.py
fvwmpy/constants.py
fvwmpy/exceptions.py
fvwmpy/fvwmpy.py
fvwmpy/log.py
fvwmpy/packet.py
fvwmpy/packet_queue.py
fvwmpy/picker.py
fvwmpy/tmp.py
fvwmpy-1.2.0.dist-info/LICENSE
fvwmpy-1.2.0.dist-info/METADATA
fvwmpy-1.2.0.dist-info/WHEEL
fvwmpy-1.2.0.dist-info/top_level.txt
fvwmpy-1.2.0.dist-info/RECORD
