Metadata-Version: 2.1
Name: fvwmpy
Version: 1.2.0
Summary: Simple and flexible interface to develop FVWM modules
Home-page: https://github.com/rostislav-matveev/FvwmPy
Author: Rostislav Matveev
Author-email: rostislav.matveev@googlemail.com
License: UNKNOWN
Project-URL: Bug Tracker, https://github.com/rostislav-matveev/FvwmPy/issues
Platform: UNKNOWN
Classifier: Development Status :: 5 - Production/Stable
Classifier: Intended Audience :: Developers
Classifier: Intended Audience :: End Users/Desktop
Classifier: License :: OSI Approved :: GNU General Public License v3 (GPLv3)
Classifier: Operating System :: POSIX :: Linux
Classifier: Programming Language :: Python :: 3.6
Classifier: Topic :: Desktop Environment :: Window Managers :: FVWM
Requires-Python: >=3.6
License-File: LICENSE
